fresh_deps/__init__.py
fresh_deps/__main__.py
fresh_deps/_dependency_updater.py
fresh_deps/_gitlab_api.py
fresh_deps/_service_api.py
fresh_deps/_update_dependencies.py
fresh_deps/py.typed
fresh_deps-1.0.0.dist-info/LICENSE
fresh_deps-1.0.0.dist-info/METADATA
fresh_deps-1.0.0.dist-info/WHEEL
fresh_deps-1.0.0.dist-info/entry_points.txt
fresh_deps-1.0.0.dist-info/top_level.txt
fresh_deps-1.0.0.dist-info/RECORD
