Metadata-Version: 2.1
Name: fresh-deps
Version: 1.0.0
Summary: Keep your Python dependencies fresh
Home-page: https://github.com/2gis-test-labs/fresh-deps
Author: 2GIS Test Labs
Author-email: test-labs@2gis.ru
Classifier: Programming Language :: Python :: 3.8
Classifier: Programming Language :: Python :: 3.9
Classifier: Programming Language :: Python :: 3.10
Classifier: Typing :: Typed
Requires-Python: >=3.8
License-File: LICENSE
Requires-Dist: pip-tools (==6.9.0)
Requires-Dist: plumbum (==1.8.0)
Requires-Dist: python-gitlab (==3.10.0)
